integrations/__init__.py
integrations/cli_wrappers/amp/amp.py
integrations/cli_wrappers/claude_code/__init__.py
integrations/cli_wrappers/claude_code/__main__.py
integrations/cli_wrappers/claude_code/claude_wrapper_v2_0.py
integrations/cli_wrappers/claude_code/config.py
integrations/cli_wrappers/claude_code/format_utils.py
integrations/cli_wrappers/claude_code/session_reset_handler.py
integrations/cli_wrappers/claude_code/wrapper.py
integrations/cli_wrappers/claude_code/detection/__init__.py
integrations/cli_wrappers/claude_code/detection/base.py
integrations/cli_wrappers/claude_code/detection/control_detector.py
integrations/cli_wrappers/claude_code/detection/permission_detector.py
integrations/cli_wrappers/claude_code/detection/plan_detector.py
integrations/cli_wrappers/claude_code/detection/question_detector.py
integrations/cli_wrappers/claude_code/messaging/__init__.py
integrations/cli_wrappers/claude_code/messaging/deduplicator.py
integrations/cli_wrappers/claude_code/messaging/input_request_manager.py
integrations/cli_wrappers/claude_code/messaging/processor.py
integrations/cli_wrappers/claude_code/messaging/queue_manager.py
integrations/cli_wrappers/claude_code/monitoring/__init__.py
integrations/cli_wrappers/claude_code/monitoring/heartbeat.py
integrations/cli_wrappers/claude_code/monitoring/idle_monitor.py
integrations/cli_wrappers/claude_code/monitoring/jsonl_monitor.py
integrations/cli_wrappers/claude_code/state/__init__.py
integrations/cli_wrappers/claude_code/state/session_state.py
integrations/cli_wrappers/claude_code/state/toggle_manager.py
integrations/cli_wrappers/claude_code/terminal/__init__.py
integrations/cli_wrappers/claude_code/terminal/ansi_cleaner.py
integrations/cli_wrappers/claude_code/terminal/buffer.py
integrations/cli_wrappers/claude_code/terminal/parser.py
integrations/cli_wrappers/claude_code/terminal/pty_manager.py
integrations/cli_wrappers/claude_code/utils/__init__.py
vicoa-1.3.0.dist-info/METADATA
vicoa-1.3.0.dist-info/WHEEL
vicoa-1.3.0.dist-info/entry_points.txt
vicoa-1.3.0.dist-info/top_level.txt
vicoa-1.3.0.dist-info/RECORD
vicoa-1.3.0.dist-info/licenses/LICENSE
vicoa-1.3.0.dist-info/sboms/auditwheel.cdx.json
