Metadata-Version: 2.4
Name: vicoa
Version: 1.3.0
Summary: Vibe Code Anywhere
Author-email: Nick <nicktay.tech@gmail.com>
License:                                  Apache License
Project-URL: Homepage, https://vicoa.ai/
Project-URL: Repository, https://github.com/vicoa-ai/vicoa-open
Project-URL: Issues, https://github.com/vicoa-ai/vicoa-open/issues
Keywords: vibe-coding,claude-code,mobile,ai,agents,codex,mcp
Classifier: Development Status :: 4 - Beta
Classifier: Intended Audience :: Developers
Classifier: Programming Language :: Python :: 3
Classifier: Programming Language :: Python :: 3.10
Classifier: Programming Language :: Python :: 3.11
Classifier: Programming Language :: Python :: 3.12
Requires-Python: >=3.10
License-File: LICENSE
Requires-Dist: requests>=2.25.0
Requires-Dist: urllib3>=2.0.0
Requires-Dist: aiohttp>=3.8.0
Requires-Dist: certifi>=2020.6.20
Requires-Dist: websocket-client>=1.6.0
Requires-Dist: fastmcp>=2.9.2
Requires-Dist: fastapi>=0.100.0
Requires-Dist: uvicorn>=0.20.0
Requires-Dist: pydantic>=2.0.0
Requires-Dist: claude-agent-sdk>=0.1.0
Requires-Dist: anthropic>=0.25.0
Requires-Dist: pathspec>=0.11.0
Dynamic: license-file
